graphql_core_promise/__init__.py
graphql_core_promise/py.typed
graphql_core_promise/execute/__init__.py
graphql_core_promise/execute/promise.py
graphql_core_promise-3.4.2.dist-info/METADATA
graphql_core_promise-3.4.2.dist-info/WHEEL
graphql_core_promise-3.4.2.dist-info/licenses/LICENSE.md
graphql_core_promise-3.4.2.dist-info/RECORD
