Metadata-Version: 2.4
Name: graphql-core-promise
Version: 3.4.2
Summary: Add support for promise-based dataloaders and resolvers to graphql-core v3+
Project-URL: Homepage, https://github.com/fellowapp/graphql-core-promise
Project-URL: Repository, https://github.com/fellowapp/graphql-core-promise
Project-URL: Changelog, https://github.com/fellowapp/graphql-core-promise/releases
Author-email: Samuel Cormier-Iijima <sam@fellow.co>, Shen Li <dustet@gmail.com>
License: BSD-3-Clause
License-File: LICENSE.md
Classifier: Development Status :: 5 - Production/Stable
Classifier: Intended Audience :: Developers
Classifier: License :: OSI Approved :: BSD License
Classifier: Operating System :: OS Independent
Classifier: Programming Language :: Python
Classifier: Programming Language :: Python :: 3 :: Only
Classifier: Programming Language :: Python :: 3.10
Classifier: Programming Language :: Python :: 3.11
Classifier: Programming Language :: Python :: 3.12
Classifier: Programming Language :: Python :: 3.13
Classifier: Topic :: Software Development :: Libraries :: Python Modules
Classifier: Typing :: Typed
Requires-Python: >=3.10
Requires-Dist: graphql-core>=3.2
Requires-Dist: promise>=2.3
